Metadata-Version: 1.0
Name: StatsPykage
Version: 1.1
Summary: Probability distributions (Gaussian and Binomial) analysis package.
Home-page: UNKNOWN
Author: VoidCodez
Author-email: UNKNOWN
License: MIT
Platform: UNKNOWN
